bones/__init__.py
bones/__main__.py
bones/__metadata__.py
bones/api.py
bones/errors.py
bones/io.py
pybones-0.1.0.dist-info/DESCRIPTION.rst
pybones-0.1.0.dist-info/METADATA
pybones-0.1.0.dist-info/RECORD
pybones-0.1.0.dist-info/WHEEL
pybones-0.1.0.dist-info/dependency_links.txt
pybones-0.1.0.dist-info/entry_points.txt
pybones-0.1.0.dist-info/metadata.json
pybones-0.1.0.dist-info/top_level.txt
