Metadata-Version: 2.0
Name: pybones
Version: 0.1.0
Summary: A python project creation toolkit
Home-page: https://github.com/brianbruggeman/bones
Author: Brian Bruggeman
Author-email: brian.m.bruggeman@gmail.com
License: Apache 2.0
Keywords: bones,scaffold,template,project,package,tool
Platform: any
Classifier: Programming Language :: Python
Classifier: Natural Language :: English
Classifier: Development Status :: 3 - Alpha
Classifier: Natural Language :: English
Classifier: Operating System :: POSIX
Classifier: Programming Language :: Python :: 3.6
Requires-Dist: GitPython
Requires-Dist: click
Requires-Dist: colorama
Requires-Dist: jinja2
Requires-Dist: requests
Provides-Extra: all
Requires-Dist: GitPython; extra == 'all'
Requires-Dist: click; extra == 'all'
Requires-Dist: colorama; extra == 'all'
Requires-Dist: ipdb; extra == 'all'
Requires-Dist: ipython; extra == 'all'
Requires-Dist: isort; extra == 'all'
Requires-Dist: jinja2; extra == 'all'
Requires-Dist: keyring; extra == 'all'
Requires-Dist: pdbpp; extra == 'all'
Requires-Dist: pip (>9); extra == 'all'
Requires-Dist: pytest; extra == 'all'
Requires-Dist: pytest-cov; extra == 'all'
Requires-Dist: pytest-flake8; extra == 'all'
Requires-Dist: pytest-isort; extra == 'all'
Requires-Dist: pytest-xdist; extra == 'all'
Requires-Dist: requests; extra == 'all'
Requires-Dist: setuptools; extra == 'all'
Requires-Dist: sphinx; extra == 'all'
Requires-Dist: sphinx-rtd-theme; extra == 'all'
Requires-Dist: sphinxcontrib-napoleon; extra == 'all'
Requires-Dist: tox; extra == 'all'
Requires-Dist: twine; extra == 'all'
Requires-Dist: wheel; extra == 'all'
Provides-Extra: debug
Requires-Dist: ipdb; extra == 'debug'
Requires-Dist: ipython; extra == 'debug'
Requires-Dist: pdbpp; extra == 'debug'
Provides-Extra: deploy
Requires-Dist: twine; extra == 'deploy'
Provides-Extra: dev
Requires-Dist: ipdb; extra == 'dev'
Requires-Dist: ipython; extra == 'dev'
Requires-Dist: isort; extra == 'dev'
Requires-Dist: keyring; extra == 'dev'
Requires-Dist: pdbpp; extra == 'dev'
Requires-Dist: pip (>9); extra == 'dev'
Requires-Dist: pytest; extra == 'dev'
Requires-Dist: pytest-cov; extra == 'dev'
Requires-Dist: pytest-flake8; extra == 'dev'
Requires-Dist: pytest-isort; extra == 'dev'
Requires-Dist: pytest-xdist; extra == 'dev'
Requires-Dist: setuptools; extra == 'dev'
Requires-Dist: sphinx; extra == 'dev'
Requires-Dist: sphinx-rtd-theme; extra == 'dev'
Requires-Dist: sphinxcontrib-napoleon; extra == 'dev'
Requires-Dist: tox; extra == 'dev'
Requires-Dist: twine; extra == 'dev'
Requires-Dist: wheel; extra == 'dev'
Provides-Extra: docs
Requires-Dist: sphinx; extra == 'docs'
Requires-Dist: sphinx-rtd-theme; extra == 'docs'
Requires-Dist: sphinxcontrib-napoleon; extra == 'docs'
Provides-Extra: pypi
Requires-Dist: keyring; extra == 'pypi'
Requires-Dist: setuptools; extra == 'pypi'
Requires-Dist: twine; extra == 'pypi'
Requires-Dist: wheel; extra == 'pypi'
Provides-Extra: tests
Requires-Dist: pytest; extra == 'tests'
Requires-Dist: pytest-cov; extra == 'tests'
Requires-Dist: pytest-flake8; extra == 'tests'
Requires-Dist: pytest-isort; extra == 'tests'
Requires-Dist: pytest-xdist; extra == 'tests'
Requires-Dist: tox; extra == 'tests'
